mewbot_dev_tools/__init__.py
mewbot_dev_tools/annotate.py
mewbot_dev_tools/dev_venv.py
mewbot_dev_tools/docs.py
mewbot_dev_tools/install_deps.py
mewbot_dev_tools/lint.py
mewbot_dev_tools/path.py
mewbot_dev_tools/preflight.py
mewbot_dev_tools/py.typed
mewbot_dev_tools/reuse.py
mewbot_dev_tools/security_analysis.py
mewbot_dev_tools/terminal.py
mewbot_dev_tools/test.py
mewbot_dev_tools/toolchain.py
mewbot_dev_tools/console_scripts/__init__.py
mewbot_dev_tools/console_scripts/mewbot_annotate.py
mewbot_dev_tools/console_scripts/mewbot_install_deps.py
mewbot_dev_tools/console_scripts/mewbot_lint.py
mewbot_dev_tools/console_scripts/mewbot_preflight.py
mewbot_dev_tools/console_scripts/mewbot_reuse.py
mewbot_dev_tools/console_scripts/mewbot_security_analysis.py
mewbot_dev_tools/console_scripts/mewbot_test.py
mewbot_dev_tools-0.0.20.dist-info/LICENSE.md
mewbot_dev_tools-0.0.20.dist-info/METADATA
mewbot_dev_tools-0.0.20.dist-info/WHEEL
mewbot_dev_tools-0.0.20.dist-info/entry_points.txt
mewbot_dev_tools-0.0.20.dist-info/top_level.txt
mewbot_dev_tools-0.0.20.dist-info/RECORD
