Metadata-Version: 2.1
Name: mewbot-dev-tools
Version: 0.0.20
Summary: Mewbot Developers Tools (https://github.com/mewbotorg)
Home-page: https://github.com/mewler/mewbot
Author: Alex Cameron
Author-email: mewbot@quicksilver.london
License: Copyright (c) <year> <owner> All rights reserved.
Project-URL: Bug Tracker, https://github.com/mewler/mewbot/issues
Classifier: Programming Language :: Python :: 3
Classifier: Operating System :: OS Independent
Requires-Python: >=3.10
License-File: LICENSE.md
Requires-Dist: setuptools >=68.0.0
Requires-Dist: reuse ~=2.1
Requires-Dist: pydeps ~=1.12.1
Requires-Dist: myst-parser ~=2.0.0
Requires-Dist: sphinx ~=7.2.2
Requires-Dist: m2r2 ~=0.3.3.post2
Requires-Dist: black >=23.1.0
Requires-Dist: flake8 >=6.0.0
Requires-Dist: pylint >=2.16.0
Requires-Dist: pytest-github-actions-annotate-failures >=0.1.7
Requires-Dist: pydocstyle >=6.3.0
Requires-Dist: isort >=5.12.0
Requires-Dist: ruff >=0.0.292
Requires-Dist: bandit ~=1.7.5
Requires-Dist: mypy >=0.991
Requires-Dist: types-PyYAML ~=6.0
Requires-Dist: clint >=0.5.1
Requires-Dist: pytest >=7.1.1
Requires-Dist: pytest-asyncio >=0.21.1
Requires-Dist: pytest-cov >=3.0.0
Requires-Dist: pytest-xdist >=2.5.0
